conav_suite/__init__.py
conav_suite/conav_suite.py
conav_suite/utils/__init__.py
conav_suite/utils/core.py
conav_suite/utils/problems.py
conav_suite/utils/scenario.py
conav_suite/utils/simple_env.py
conav_suite-0.0.2.dist-info/licenses/LICENSE
conav_suite-0.0.2.dist-info/METADATA
conav_suite-0.0.2.dist-info/WHEEL
conav_suite-0.0.2.dist-info/top_level.txt
conav_suite-0.0.2.dist-info/RECORD
