Metadata-Version: 2.4
Name: conav_suite
Version: 0.0.2
Summary: A problem suite focused on evaluating the ability of autonomous agents to develop emergent communication strategies in cooperative navigation tasks
Home-page: https://github.com/ethanmclark1/conav_suite
Author: Ethan Clark
Author-email: eclark715@gmail.com.com
Classifier: License :: OSI Approved :: MIT License
Classifier: Programming Language :: Python
License-File: LICENSE
Dynamic: author
Dynamic: author-email
Dynamic: classifier
Dynamic: description
Dynamic: description-content-type
Dynamic: home-page
Dynamic: license-file
Dynamic: summary
